{
    "skyboxes": [
        { "label": "Abandoned tank farm", "url": "./skybox/abandoned_tank_farm_01_2k.hdr" },
        { "label": "Ballroom", "url": "./skybox/ballroom_2k.hdr" },
        { "label": "Circus Arena", "url": "./skybox/circus_arena_2k.hdr" },
        { "label": "Helipad", "url": "./skybox/Helipad_equi.png" },
        { "label": "Kloppenheim", "url": "./skybox/kloppenheim_02_2k.hdr" },
        { "label": "Outdoor Umbrellas", "url": "./skybox/outdoor_umbrellas_2k.hdr" },
        { "label": "Spruit sunrise", "url": "./skybox/spruit_sunrise_2k.hdr" },
        { "label": "Studio small", "url": "./skybox/studio_small_03_2k.hdr" },
        { "label": "Sunset", "url": "./skybox/sunset.hdr" },
        { "label": "Vignaioli night", "url": "./skybox/vignaioli_night_2k.hdr" },
        { "label": "Wooden motel", "url": "./skybox/wooden_motel_2k.hdr" }
    ]
}
