{"mapping_format": "path", "name": "Playbot_head", "parameters": [{"data": [0.588, 0.588, 0.588], "type": "vec3", "name": "ambient"}, {"data": "../2520c110-ea64-11e3-bd92-22000a4a0339/head_clean.png", "type": "texture", "name": "diffuseMap"}, {"data": [0.9, 0.9, 0.9], "type": "vec3", "name": "specular"}, {"data": 1024, "type": "float", "name": "shininess"}, {"data": "../2b606346-ea64-11e3-bd92-22000a4a0339/head_E.png", "type": "texture", "name": "emissiveMap"}, {"data": "../2a9a58c2-ea64-11e3-bd92-22000a4a0339/head_N_clean.png", "type": "texture", "name": "normalMap"}, {"data": 0.3, "type": "float", "name": "bumpMapFactor"}, {"data": 1, "type": "float", "name": "opacity"}, {"data": "../2a45d5b8-ea64-11e3-bd92-22000a4a0339/env_01.png", "type": "texture", "name": "sphereMap"}, {"data": 0.2, "type": "float", "name": "reflectivity"}], "shader": "phong"}