{
  "entities" : {
    "1" : {
      "name" : "Cone",
      "tags" : [],
      "enabled" : true,
      "resource_id" : "1",
      "parent" : null,
      "children" : [],
      "position" : [
        0,
        1.07061147689819,
        0
      ],
      "rotation" : [
        0,
        0,
        0
      ],
      "scale" : [
        0.5,
        0.5,
        1
      ],
      "components" : {
        "model" : {
          "enabled" : true,
          "type" : "cone",
          "asset" : null,
          "materialAsset" : null,
          "castShadows" : true,
          "castShadowsLightmap" : true,
          "lightmapped" : false,
          "lightmapSizeMultiplier" : 1,
          "castShadowsLightMap" : true,
          "lightMapped" : false,
          "lightMapSizeMultiplier" : 1,
          "isStatic" : false,
          "layers" : [
            0
          ],
          "batchGroupId" : null
        }
      }
    }
  }
}